sheetreader/SheetReader.py
sheetreader/__init__.py
sheetreader/google_sheets_api.py
sheetreader-0.0.1.dist-info/RECORD
sheetreader-0.0.1.dist-info/metadata.json
sheetreader-0.0.1.dist-info/WHEEL
sheetreader-0.0.1.dist-info/DESCRIPTION.rst
sheetreader-0.0.1.dist-info/top_level.txt
sheetreader-0.0.1.dist-info/METADATA
